{
 "actions": [],
 "allow_rename": 1,
 "creation": "2025-10-08 18:47:18.782476",
 "doctype": "DocType",
 "editable_grid": 1,
 "engine": "InnoDB",
 "field_order": [
  "item_code",
  "item_name",
  "qty",
  "item_date",
  "gov_charge",
  "service_charge",
  "amount",
  "status",
  "payment_type",
  "row_id",
  "remarks"
 ],
 "fields": [
  {
   "fieldname": "item_code",
   "fieldtype": "Link",
   "in_global_search": 1,
   "in_list_view": 1,
   "label": "Item",
   "options": "Item",
   "print_width": "150px",
   "reqd": 1,
   "width": "150px"
  },
  {
   "default": "1",
   "fieldname": "qty",
   "fieldtype": "Float",
   "in_list_view": 1,
   "label": "Qty",
   "non_negative": 1,
   "print_width": "100px",
   "reqd": 1,
   "width": "100px"
  },
  {
   "fieldname": "gov_charge",
   "fieldtype": "Currency",
   "in_list_view": 1,
   "label": "Gov Charge"
  },
  {
   "fieldname": "service_charge",
   "fieldtype": "Currency",
   "in_list_view": 1,
   "label": "Service Charge"
  },
  {
   "fieldname": "payment_type",
   "fieldtype": "Link",
   "label": "Payment Type",
   "mandatory_depends_on": "eval:doc.status==\"Completed\"\n",
   "options": "Mode of Payment",
   "print_hide": 1
  },
  {
   "fieldname": "status",
   "fieldtype": "Select",
   "label": "Status",
   "options": "Pending\nWaiting For Payment\nCompleted",
   "print_hide": 1,
   "read_only_depends_on": "\n",
   "reqd": 1
  },
  {
   "fieldname": "remarks",
   "fieldtype": "Small Text",
   "label": "Remarks"
  },
  {
   "fieldname": "amount",
   "fieldtype": "Currency",
   "label": "Amount",
   "read_only": 1
  },
  {
   "fieldname": "item_name",
   "fieldtype": "Data",
   "label": "Item Name"
  },
  {
   "fieldname": "row_id",
   "fieldtype": "Int",
   "hidden": 1,
   "label": "Row ID",
   "read_only": 1
  },
  {
   "fieldname": "item_date",
   "fieldtype": "Date",
   "label": "Date"
  }
 ],
 "grid_page_length": 50,
 "index_web_pages_for_search": 1,
 "istable": 1,
 "links": [],
 "modified": "2025-11-20 15:13:20.391887",
 "modified_by": "Administrator",
 "module": "Ag Docs",
 "name": "Service Request Item",
 "owner": "ytopsharafu@gmail.com",
 "permissions": [],
 "row_format": "Dynamic",
 "rows_threshold_for_grid_search": 20,
 "sort_field": "modified",
 "sort_order": "DESC",
 "states": []
}